README.md
setup.py
feedoo/__init__.py
feedoo/abstract_action.py
feedoo/abstract_input_db.py
feedoo/abstract_output_db.py
feedoo/action_states.py
feedoo/cli.py
feedoo/configuration.py
feedoo/event.py
feedoo/feed_manager.py
feedoo/feedoo.py
feedoo/feedoo_states.py
feedoo/hash_storage.py
feedoo/intervals.py
feedoo/pipeline_mp.py
feedoo/pipeline_sp.py
feedoo/plugins.py
feedoo/privileges.py
feedoo/rethinkdb_adapter.py
feedoo/sqlite_adapter.py
feedoo/time_frame.py
feedoo.egg-info/PKG-INFO
feedoo.egg-info/SOURCES.txt
feedoo.egg-info/dependency_links.txt
feedoo.egg-info/entry_points.txt
feedoo.egg-info/not-zip-safe
feedoo.egg-info/requires.txt
feedoo.egg-info/top_level.txt
feedoo/filter/__init__.py
feedoo/filter/filter_change.py
feedoo/filter/filter_date.py
feedoo/filter/filter_dnsbl.py
feedoo/filter/filter_flatline.py
feedoo/filter/filter_frequency.py
feedoo/filter/filter_matching_list.py
feedoo/filter/filter_remove_keys.py
feedoo/filter/filter_rename.py
feedoo/filter/filter_retag.py
feedoo/filter/filter_spike.py
feedoo/input/__init__.py
feedoo/input/input_dummy.py
feedoo/input/input_file.py
feedoo/input/input_forward.py
feedoo/input/input_rethinkdb.py
feedoo/input/input_sqlite.py
feedoo/output/__init__.py
feedoo/output/output_archive.py
feedoo/output/output_rethinkdb.py
feedoo/output/output_sqlite.py
feedoo/output/output_stdout.py
feedoo/parser/__init__.py
feedoo/parser/parser_json.py
feedoo/parser/parser_regex.py