Metadata-Version: 2.1
Name: feedoo
Version: 0.6.0
Summary: General purpose data processor
Home-page: https://github.com/laulin/feedoo
Author: Laurent MOULIN
Author-email: gignops@gmail.com
License: GPLV3
Platform: UNKNOWN
Classifier: Programming Language :: Python :: 3
Classifier: License :: OSI Approved :: GNU General Public License v3 or later (GPLv3+)
Classifier: Operating System :: OS Independent
Classifier: Development Status :: 4 - Beta
Classifier: Intended Audience :: Information Technology
Classifier: Topic :: Internet :: Log Analysis
Requires-Python: >=3
